sockData/__init__.py
sockData/datatype.py
sockData/receive.py
sockData/send.py
sockData-1.0.1.dist-info/METADATA
sockData-1.0.1.dist-info/RECORD
sockData-1.0.1.dist-info/WHEEL
sockData-1.0.1.dist-info/top_level.txt
