Metadata-Version: 2.1
Name: sockData
Version: 1.0.1
Summary: Socket extension
Home-page: https://github.com/letsCodeMyLife/sockData/
Author: Henning Arvid Ladewig
Author-email: anne@opentrash.com
License: UNKNOWN
Platform: UNKNOWN
